tunnelis_core/__init__.py
tunnelis_core/messages/__init__.py
tunnelis_core/messages/builders.py
tunnelis_core/messages/messages_pb2.py
tunnelis_core/sockets/__init__.py
tunnelis_core/sockets/client.py
tunnelis_core/sockets/publisher.py
tunnelis_core/sockets/server.py
tunnelis_core/sockets/subscriber.py
tunnelis_core/sockets/tcp.py
tunnelis_core/utils/__init__.py
tunnelis_core/utils/utils.py
tunnelis_core-1.6.4.dist-info/METADATA
tunnelis_core-1.6.4.dist-info/WHEEL
tunnelis_core-1.6.4.dist-info/top_level.txt
tunnelis_core-1.6.4.dist-info/RECORD
