Metadata-Version: 2.1
Name: tunnelis-core
Version: 1.6.4
Summary: Python package containing common classes and data structures required by Tunnelis.
Home-page: UNKNOWN
Author: Pedro Melo, Rafael Arrais, Sergio Marinho
Author-email: pedro.m.melo@inesctec.pt, rafael.l.arrais@inesctec.pt, sergio.d.marinho@inesctec.pt
License: UNKNOWN
Platform: UNKNOWN
Classifier: Programming Language :: Python :: 3
Requires-Python: >=3.6
Requires-Dist: grpcio
Requires-Dist: grpcio-tools
Requires-Dist: tornado
Requires-Dist: zmq
